netbox_friendlyurl/__init__.py
netbox_friendlyurl/middleware.py
netbox_friendlyurl/urls.py
netbox_friendlyurl/views.py
netbox_friendlyurl-0.1.dist-info/LICENSE
netbox_friendlyurl-0.1.dist-info/METADATA
netbox_friendlyurl-0.1.dist-info/WHEEL
netbox_friendlyurl-0.1.dist-info/top_level.txt
netbox_friendlyurl-0.1.dist-info/RECORD
