Metadata-Version: 2.1
Name: netbox-friendlyurl
Version: 0.1
Summary: Netbox Friendly URLs
License-File: LICENSE
